stormfield/__init__.py
stormfield/stormfield.py
stormfield-1.2.6.dist-info/licenses/LICENSE
stormfield-1.2.6.dist-info/METADATA
stormfield-1.2.6.dist-info/WHEEL
stormfield-1.2.6.dist-info/top_level.txt
stormfield-1.2.6.dist-info/RECORD
