Metadata-Version: 2.4
Name: stormfield
Version: 1.2.6
Summary: A simple collision library for pygame inspired by LÖVE2D's windfield
Home-page: https://github.com/clxakz/stormfield
Author: clxakz
License: MIT
Classifier: Programming Language :: Python :: 3
Classifier: License :: OSI Approved :: MIT License
Classifier: Operating System :: OS Independent
Requires-Python: >=3.7
License-File: LICENSE
Requires-Dist: pygame-ce
Dynamic: author
Dynamic: classifier
Dynamic: description
Dynamic: description-content-type
Dynamic: home-page
Dynamic: license
Dynamic: license-file
Dynamic: requires-dist
Dynamic: requires-python
Dynamic: summary
